ai_games/__init__.py
ai_games/connect4.py
ai_games-0.1.6.dist-info/METADATA
ai_games-0.1.6.dist-info/WHEEL
ai_games-0.1.6.dist-info/top_level.txt
ai_games-0.1.6.dist-info/RECORD
