Metadata-Version: 2.1
Name: ai_games
Version: 0.1.6
Summary: AI Games: Collection of interactive games with AI opponents for Python.
Home-page: https://github.com/bzm10/ai_games
Author: Coding with BM
Classifier: Programming Language :: Python :: 3
Classifier: License :: OSI Approved :: MIT License
Classifier: Operating System :: OS Independent
Requires-Dist: pygame
